{
    "subject": "Vendo Apartamento 78m2, 2 Quartos, Reformado- Vila Isabel-RJ",
    "title": "Vendo Apartamento 78m2, 2 Quartos, Reformado- Vila Isabel-RJ",
    "price": "R$ 310.000",
    "listId": 1362154774,
    "lastBumpAgeSecs": "0",
    "oldPrice": null,
    "professionalAd": true,
    "priceReductionBadge": false,
    "userGoogleReviewsVisible": false,
    "userGoogleRating": null,
    "isFeatured": false,
    "listingCategoryId": "1001",
    "images": [
        {
            "original": "https://img.olx.com.br/images/10/102464231046225.jpg",
            "originalAlt": "Vendo Apartamento 78m2, 2 Quartos, Reformado- Vila Isabel-RJ",
            "originalWebP": "https://img.olx.com.br/images/10/102464231046225.webp",
            "thumbnail": "https://img.olx.com.br/thumbs/10/102464231046225.jpg"
        },
        {
            "original": "https://img.olx.com.br/images/10/107488836972389.jpg",
            "originalAlt": "Vendo Apartamento 78m2, 2 Quartos, Reformado- Vila Isabel-RJ - Foto 2",
            "originalWebP": "https://img.olx.com.br/images/10/107488836972389.webp",
            "thumbnail": "https://img.olx.com.br/thumbs/10/107488836972389.jpg"
        },
        {
            "original": "https://img.olx.com.br/images/10/108462595457742.jpg",
            "originalAlt": "Vendo Apartamento 78m2, 2 Quartos, Reformado- Vila Isabel-RJ - Foto 3",
            "originalWebP": "https://img.olx.com.br/images/10/108462595457742.webp",
            "thumbnail": "https://img.olx.com.br/thumbs/10/108462595457742.jpg"
        },
        {
            "original": "https://img.olx.com.br/images/10/102428230656623.jpg",
            "originalAlt": "Vendo Apartamento 78m2, 2 Quartos, Reformado- Vila Isabel-RJ - Foto 4",
            "originalWebP": "https://img.olx.com.br/images/10/102428230656623.webp",
            "thumbnail": "https://img.olx.com.br/thumbs/10/102428230656623.jpg"
        },
        {
            "original": "https://img.olx.com.br/images/10/106413477310410.jpg",
            "originalAlt": "Vendo Apartamento 78m2, 2 Quartos, Reformado- Vila Isabel-RJ - Foto 5",
            "originalWebP": "https://img.olx.com.br/images/10/106413477310410.webp",
            "thumbnail": "https://img.olx.com.br/thumbs/10/106413477310410.jpg"
        },
        {
            "original": "https://img.olx.com.br/images/10/103456358106690.jpg",
            "originalAlt": "Vendo Apartamento 78m2, 2 Quartos, Reformado- Vila Isabel-RJ - Foto 6",
            "originalWebP": "https://img.olx.com.br/images/10/103456358106690.webp",
            "thumbnail": "https://img.olx.com.br/thumbs/10/103456358106690.jpg"
        },
        {
            "original": "https://img.olx.com.br/images/10/104450710326752.jpg",
            "originalAlt": "Vendo Apartamento 78m2, 2 Quartos, Reformado- Vila Isabel-RJ - Foto 7",
            "originalWebP": "https://img.olx.com.br/images/10/104450710326752.webp",
            "thumbnail": "https://img.olx.com.br/thumbs/10/104450710326752.jpg"
        },
        {
            "original": "https://img.olx.com.br/images/10/106470470489213.jpg",
            "originalAlt": "Vendo Apartamento 78m2, 2 Quartos, Reformado- Vila Isabel-RJ - Foto 8",
            "originalWebP": "https://img.olx.com.br/images/10/106470470489213.webp",
            "thumbnail": "https://img.olx.com.br/thumbs/10/106470470489213.jpg"
        },
        {
            "original": "https://img.olx.com.br/images/10/100418598418338.jpg",
            "originalAlt": "Vendo Apartamento 78m2, 2 Quartos, Reformado- Vila Isabel-RJ - Foto 9",
            "originalWebP": "https://img.olx.com.br/images/10/100418598418338.webp",
            "thumbnail": "https://img.olx.com.br/thumbs/10/100418598418338.jpg"
        },
        {
            "original": "https://img.olx.com.br/images/10/102453477774412.jpg",
            "originalAlt": "Vendo Apartamento 78m2, 2 Quartos, Reformado- Vila Isabel-RJ - Foto 10",
            "originalWebP": "https://img.olx.com.br/images/10/102453477774412.webp",
            "thumbnail": "https://img.olx.com.br/thumbs/10/102453477774412.jpg"
        },
        {
            "original": "https://img.olx.com.br/images/10/106424835951306.jpg",
            "originalAlt": "Vendo Apartamento 78m2, 2 Quartos, Reformado- Vila Isabel-RJ - Foto 11",
            "originalWebP": "https://img.olx.com.br/images/10/106424835951306.webp",
            "thumbnail": "https://img.olx.com.br/thumbs/10/106424835951306.jpg"
        },
        {
            "original": "https://img.olx.com.br/images/10/107429954000336.jpg",
            "originalAlt": "Vendo Apartamento 78m2, 2 Quartos, Reformado- Vila Isabel-RJ - Foto 12",
            "originalWebP": "https://img.olx.com.br/images/10/107429954000336.webp",
            "thumbnail": "https://img.olx.com.br/thumbs/10/107429954000336.jpg"
        },
        {
            "original": "https://img.olx.com.br/images/10/109453111625801.jpg",
            "originalAlt": "Vendo Apartamento 78m2, 2 Quartos, Reformado- Vila Isabel-RJ - Foto 13",
            "originalWebP": "https://img.olx.com.br/images/10/109453111625801.webp",
            "thumbnail": "https://img.olx.com.br/thumbs/10/109453111625801.jpg"
        },
        {
            "original": "https://img.olx.com.br/images/10/101431832990973.jpg",
            "originalAlt": "Vendo Apartamento 78m2, 2 Quartos, Reformado- Vila Isabel-RJ - Foto 14",
            "originalWebP": "https://img.olx.com.br/images/10/101431832990973.webp",
            "thumbnail": "https://img.olx.com.br/thumbs/10/101431832990973.jpg"
        },
        {
            "original": "https://img.olx.com.br/images/10/105486957147569.jpg",
            "originalAlt": "Vendo Apartamento 78m2, 2 Quartos, Reformado- Vila Isabel-RJ - Foto 15",
            "originalWebP": "https://img.olx.com.br/images/10/105486957147569.webp",
            "thumbnail": "https://img.olx.com.br/thumbs/10/105486957147569.jpg"
        },
        {
            "original": "https://img.olx.com.br/images/10/102460596268598.jpg",
            "originalAlt": "Vendo Apartamento 78m2, 2 Quartos, Reformado- Vila Isabel-RJ - Foto 16",
            "originalWebP": "https://img.olx.com.br/images/10/102460596268598.webp",
            "thumbnail": "https://img.olx.com.br/thumbs/10/102460596268598.jpg"
        },
        {
            "original": "https://img.olx.com.br/images/10/101436113900205.jpg",
            "originalAlt": "Vendo Apartamento 78m2, 2 Quartos, Reformado- Vila Isabel-RJ - Foto 17",
            "originalWebP": "https://img.olx.com.br/images/10/101436113900205.webp",
            "thumbnail": "https://img.olx.com.br/thumbs/10/101436113900205.jpg"
        },
        {
            "original": "https://img.olx.com.br/images/10/105481112206578.jpg",
            "originalAlt": "Vendo Apartamento 78m2, 2 Quartos, Reformado- Vila Isabel-RJ - Foto 18",
            "originalWebP": "https://img.olx.com.br/images/10/105481112206578.webp",
            "thumbnail": "https://img.olx.com.br/thumbs/10/105481112206578.jpg"
        },
        {
            "original": "https://img.olx.com.br/images/10/102437958491949.jpg",
            "originalAlt": "Vendo Apartamento 78m2, 2 Quartos, Reformado- Vila Isabel-RJ - Foto 19",
            "originalWebP": "https://img.olx.com.br/images/10/102437958491949.webp",
            "thumbnail": "https://img.olx.com.br/thumbs/10/102437958491949.jpg"
        },
        {
            "original": "https://img.olx.com.br/images/11/113413593185379.jpg",
            "originalAlt": "Vendo Apartamento 78m2, 2 Quartos, Reformado- Vila Isabel-RJ - Foto 20",
            "originalWebP": "https://img.olx.com.br/images/11/113413593185379.webp",
            "thumbnail": "https://img.olx.com.br/thumbs/11/113413593185379.jpg"
        }
    ],
    "videoCount": 0,
    "isChatEnabled": false,
    "fixedOnTop": false,
    "url": "https://rj.olx.com.br/rio-de-janeiro-e-regiao/imoveis/vendo-apartamento-78m2-2-quartos-reformado-vila-isabel-rj-1362154774",
    "thumbnail": "https://img.olx.com.br/thumbs256x256/10/102464231046225.jpg",
    "date": 1734035916,
    "imageCount": 20,
    "location": "Rio de Janeiro, Vila Isabel",
    "locationDetails": {
        "municipality": "Rio de Janeiro",
        "ddd": "21",
        "neighbourhood": "Vila Isabel",
        "uf": "RJ"
    },
    "category": "Apartamentos",
    "searchCategoryLevelZero": 1000,
    "searchCategoryLevelOne": 1001,
    "properties": [
        {
            "name": "category",
            "label": "Categoria",
            "value": "Apartamentos"
        },
        {
            "name": "real_estate_type",
            "label": "Tipo",
            "value": "Venda - apartamento padrão"
        },
        {
            "name": "condominio",
            "label": "Condomínio",
            "value": "R$ 900"
        },
        {
            "name": "iptu",
            "label": "IPTU",
            "value": "R$ 80"
        },
        {
            "name": "size",
            "label": "Área útil",
            "value": "78m²"
        },
        {
            "name": "rooms",
            "label": "Quartos",
            "value": "2"
        },
        {
            "name": "bathrooms",
            "label": "Banheiros",
            "value": "2"
        },
        {
            "name": "garage_spaces",
            "label": "Vagas na garagem",
            "value": "0"
        },
        {
            "name": "re_features",
            "label": "Detalhes do imóvel",
            "value": "Área de serviço, Armários na cozinha, Armários no quarto"
        },
        {
            "name": "re_complex_features",
            "label": "Detalhes do condomínio",
            "value": "Condomínio fechado, Permitido animais"
        },
        {
            "name": "re_types",
            "label": "Tipo",
            "value": "Padrão"
        }
    ],
    "accountActivityStatus": {
        "isOnline": false
    },
    "position": 28,
    "olxPay": {
        "enabled": false,
        "dynamicBadgeProps": [],
        "transactionalBadges": [],
        "installments": [],
        "isCategoryEligible": false
    },
    "olxPayBadgeEnabled": false,
    "olxDelivery": {
        "enabled": false,
        "weight": null
    },
    "olxDeliveryBadgeEnabled": false,
    "installments": false,
    "vehicleReport": {
        "enabled": false,
        "title": null,
        "description": null,
        "reportLink": null,
        "reportTitle": null,
        "tags": null
    },
    "vehicleTags": [],
    "vehicleHasInspectionReport": false,
    "vehiclePills": null,
    "isFavorited": false,
    "hasRealEstateHighlight": false,
    "trackingSpecificData": [
        {
            "key": "region",
            "value": "Rio de Janeiro e região"
        }
    ],
    "carSpecificData": null
}