{
    "subject": "Apartamento-À VENDA-Centro-Rio de Janeiro-RJ",
    "title": "Apartamento-À VENDA-Centro-Rio de Janeiro-RJ",
    "price": "R$ 510.000",
    "listId": 1362226815,
    "lastBumpAgeSecs": "0",
    "oldPrice": null,
    "professionalAd": true,
    "priceReductionBadge": false,
    "userGoogleReviewsVisible": false,
    "userGoogleRating": null,
    "isFeatured": false,
    "listingCategoryId": "1001",
    "images": [
        {
            "original": "https://img.olx.com.br/images/82/823493713698314.jpg",
            "originalAlt": "Apartamento-À VENDA-Centro-Rio de Janeiro-RJ",
            "originalWebP": "https://img.olx.com.br/images/82/823493713698314.webp",
            "thumbnail": "https://img.olx.com.br/thumbs/82/823493713698314.jpg"
        },
        {
            "original": "https://img.olx.com.br/images/81/810463478071870.jpg",
            "originalAlt": "Apartamento-À VENDA-Centro-Rio de Janeiro-RJ - Foto 2",
            "originalWebP": "https://img.olx.com.br/images/81/810463478071870.webp",
            "thumbnail": "https://img.olx.com.br/thumbs/81/810463478071870.jpg"
        },
        {
            "original": "https://img.olx.com.br/images/82/828473357301994.jpg",
            "originalAlt": "Apartamento-À VENDA-Centro-Rio de Janeiro-RJ - Foto 3",
            "originalWebP": "https://img.olx.com.br/images/82/828473357301994.webp",
            "thumbnail": "https://img.olx.com.br/thumbs/82/828473357301994.jpg"
        },
        {
            "original": "https://img.olx.com.br/images/81/811481955773951.jpg",
            "originalAlt": "Apartamento-À VENDA-Centro-Rio de Janeiro-RJ - Foto 4",
            "originalWebP": "https://img.olx.com.br/images/81/811481955773951.webp",
            "thumbnail": "https://img.olx.com.br/thumbs/81/811481955773951.jpg"
        },
        {
            "original": "https://img.olx.com.br/images/81/815429357836446.jpg",
            "originalAlt": "Apartamento-À VENDA-Centro-Rio de Janeiro-RJ - Foto 5",
            "originalWebP": "https://img.olx.com.br/images/81/815429357836446.webp",
            "thumbnail": "https://img.olx.com.br/thumbs/81/815429357836446.jpg"
        },
        {
            "original": "https://img.olx.com.br/images/81/815494711158456.jpg",
            "originalAlt": "Apartamento-À VENDA-Centro-Rio de Janeiro-RJ - Foto 6",
            "originalWebP": "https://img.olx.com.br/images/81/815494711158456.webp",
            "thumbnail": "https://img.olx.com.br/thumbs/81/815494711158456.jpg"
        },
        {
            "original": "https://img.olx.com.br/images/81/816423119634207.jpg",
            "originalAlt": "Apartamento-À VENDA-Centro-Rio de Janeiro-RJ - Foto 7",
            "originalWebP": "https://img.olx.com.br/images/81/816423119634207.webp",
            "thumbnail": "https://img.olx.com.br/thumbs/81/816423119634207.jpg"
        },
        {
            "original": "https://img.olx.com.br/images/81/812471233608917.jpg",
            "originalAlt": "Apartamento-À VENDA-Centro-Rio de Janeiro-RJ - Foto 8",
            "originalWebP": "https://img.olx.com.br/images/81/812471233608917.webp",
            "thumbnail": "https://img.olx.com.br/thumbs/81/812471233608917.jpg"
        },
        {
            "original": "https://img.olx.com.br/images/81/813436832326492.jpg",
            "originalAlt": "Apartamento-À VENDA-Centro-Rio de Janeiro-RJ - Foto 9",
            "originalWebP": "https://img.olx.com.br/images/81/813436832326492.webp",
            "thumbnail": "https://img.olx.com.br/thumbs/81/813436832326492.jpg"
        },
        {
            "original": "https://img.olx.com.br/images/82/829494472335663.jpg",
            "originalAlt": "Apartamento-À VENDA-Centro-Rio de Janeiro-RJ - Foto 10",
            "originalWebP": "https://img.olx.com.br/images/82/829494472335663.webp",
            "thumbnail": "https://img.olx.com.br/thumbs/82/829494472335663.jpg"
        },
        {
            "original": "https://img.olx.com.br/images/81/814408598331757.jpg",
            "originalAlt": "Apartamento-À VENDA-Centro-Rio de Janeiro-RJ - Foto 11",
            "originalWebP": "https://img.olx.com.br/images/81/814408598331757.webp",
            "thumbnail": "https://img.olx.com.br/thumbs/81/814408598331757.jpg"
        },
        {
            "original": "https://img.olx.com.br/images/81/813448237251570.jpg",
            "originalAlt": "Apartamento-À VENDA-Centro-Rio de Janeiro-RJ - Foto 12",
            "originalWebP": "https://img.olx.com.br/images/81/813448237251570.webp",
            "thumbnail": "https://img.olx.com.br/thumbs/81/813448237251570.jpg"
        },
        {
            "original": "https://img.olx.com.br/images/82/823493593812564.jpg",
            "originalAlt": "Apartamento-À VENDA-Centro-Rio de Janeiro-RJ - Foto 13",
            "originalWebP": "https://img.olx.com.br/images/82/823493593812564.webp",
            "thumbnail": "https://img.olx.com.br/thumbs/82/823493593812564.jpg"
        },
        {
            "original": "https://img.olx.com.br/images/82/829464714371748.jpg",
            "originalAlt": "Apartamento-À VENDA-Centro-Rio de Janeiro-RJ - Foto 14",
            "originalWebP": "https://img.olx.com.br/images/82/829464714371748.webp",
            "thumbnail": "https://img.olx.com.br/thumbs/82/829464714371748.jpg"
        },
        {
            "original": "https://img.olx.com.br/images/82/827412591144026.jpg",
            "originalAlt": "Apartamento-À VENDA-Centro-Rio de Janeiro-RJ - Foto 15",
            "originalWebP": "https://img.olx.com.br/images/82/827412591144026.webp",
            "thumbnail": "https://img.olx.com.br/thumbs/82/827412591144026.jpg"
        },
        {
            "original": "https://img.olx.com.br/images/81/811419356926492.jpg",
            "originalAlt": "Apartamento-À VENDA-Centro-Rio de Janeiro-RJ - Foto 16",
            "originalWebP": "https://img.olx.com.br/images/81/811419356926492.webp",
            "thumbnail": "https://img.olx.com.br/thumbs/81/811419356926492.jpg"
        },
        {
            "original": "https://img.olx.com.br/images/81/818457472200757.jpg",
            "originalAlt": "Apartamento-À VENDA-Centro-Rio de Janeiro-RJ - Foto 17",
            "originalWebP": "https://img.olx.com.br/images/81/818457472200757.webp",
            "thumbnail": "https://img.olx.com.br/thumbs/81/818457472200757.jpg"
        },
        {
            "original": "https://img.olx.com.br/images/82/826488710740247.jpg",
            "originalAlt": "Apartamento-À VENDA-Centro-Rio de Janeiro-RJ - Foto 18",
            "originalWebP": "https://img.olx.com.br/images/82/826488710740247.webp",
            "thumbnail": "https://img.olx.com.br/thumbs/82/826488710740247.jpg"
        },
        {
            "original": "https://img.olx.com.br/images/82/826443239909536.jpg",
            "originalAlt": "Apartamento-À VENDA-Centro-Rio de Janeiro-RJ - Foto 19",
            "originalWebP": "https://img.olx.com.br/images/82/826443239909536.webp",
            "thumbnail": "https://img.olx.com.br/thumbs/82/826443239909536.jpg"
        },
        {
            "original": "https://img.olx.com.br/images/81/810455597497649.jpg",
            "originalAlt": "Apartamento-À VENDA-Centro-Rio de Janeiro-RJ - Foto 20",
            "originalWebP": "https://img.olx.com.br/images/81/810455597497649.webp",
            "thumbnail": "https://img.olx.com.br/thumbs/81/810455597497649.jpg"
        }
    ],
    "videoCount": 0,
    "isChatEnabled": false,
    "fixedOnTop": false,
    "url": "https://rj.olx.com.br/rio-de-janeiro-e-regiao/imoveis/apartamento-venda-centro-rio-de-janeiro-rj-1362226815",
    "thumbnail": "https://img.olx.com.br/thumbs256x256/82/823493713698314.jpg",
    "date": 1734052399,
    "imageCount": 20,
    "location": "Rio de Janeiro, Centro",
    "locationDetails": {
        "municipality": "Rio de Janeiro",
        "ddd": "21",
        "neighbourhood": "Centro",
        "uf": "RJ"
    },
    "category": "Apartamentos",
    "searchCategoryLevelZero": 1000,
    "searchCategoryLevelOne": 1001,
    "properties": [
        {
            "name": "category",
            "label": "Categoria",
            "value": "Apartamentos"
        },
        {
            "name": "real_estate_type",
            "label": "Tipo",
            "value": "Venda - apartamento padrão"
        },
        {
            "name": "condominio",
            "label": "Condomínio",
            "value": "R$ 500"
        },
        {
            "name": "iptu",
            "label": "IPTU",
            "value": "R$ 1.203"
        },
        {
            "name": "size",
            "label": "Área útil",
            "value": "45m²"
        },
        {
            "name": "rooms",
            "label": "Quartos",
            "value": "1"
        },
        {
            "name": "bathrooms",
            "label": "Banheiros",
            "value": "1"
        },
        {
            "name": "garage_spaces",
            "label": "Vagas na garagem",
            "value": "1"
        },
        {
            "name": "re_features",
            "label": "Detalhes do imóvel",
            "value": "Academia, Churrasqueira, Piscina, Varanda"
        },
        {
            "name": "re_complex_features",
            "label": "Detalhes do condomínio",
            "value": "Academia, Elevador, Piscina, Portaria, Salão de festas"
        },
        {
            "name": "re_types",
            "label": "Tipo",
            "value": "Padrão"
        }
    ],
    "accountActivityStatus": {
        "isOnline": false
    },
    "position": 48,
    "olxPay": {
        "enabled": false,
        "dynamicBadgeProps": [],
        "transactionalBadges": [],
        "installments": [],
        "isCategoryEligible": false
    },
    "olxPayBadgeEnabled": false,
    "olxDelivery": {
        "enabled": false,
        "weight": null
    },
    "olxDeliveryBadgeEnabled": false,
    "installments": false,
    "vehicleReport": {
        "enabled": false,
        "title": null,
        "description": null,
        "reportLink": null,
        "reportTitle": null,
        "tags": null
    },
    "vehicleTags": [],
    "vehicleHasInspectionReport": false,
    "vehiclePills": null,
    "isFavorited": false,
    "hasRealEstateHighlight": false,
    "trackingSpecificData": [
        {
            "key": "region",
            "value": "Rio de Janeiro e região"
        }
    ],
    "carSpecificData": null
}