{
    "subject": "Apartamento - / Residencial / Centro",
    "title": "Apartamento - / Residencial / Centro",
    "price": "R$ 465.000",
    "listId": 1362227309,
    "lastBumpAgeSecs": "0",
    "oldPrice": null,
    "professionalAd": true,
    "priceReductionBadge": false,
    "userGoogleReviewsVisible": false,
    "userGoogleRating": null,
    "isFeatured": false,
    "listingCategoryId": "1001",
    "images": [
        {
            "original": "https://img.olx.com.br/images/74/741450235160074.jpg",
            "originalAlt": "Apartamento - / Residencial / Centro",
            "originalWebP": "https://img.olx.com.br/images/74/741450235160074.webp",
            "thumbnail": "https://img.olx.com.br/thumbs/74/741450235160074.jpg"
        },
        {
            "original": "https://img.olx.com.br/images/74/745436594988517.jpg",
            "originalAlt": "Apartamento - / Residencial / Centro - Foto 2",
            "originalWebP": "https://img.olx.com.br/images/74/745436594988517.webp",
            "thumbnail": "https://img.olx.com.br/thumbs/74/745436594988517.jpg"
        },
        {
            "original": "https://img.olx.com.br/images/74/740483478101099.jpg",
            "originalAlt": "Apartamento - / Residencial / Centro - Foto 3",
            "originalWebP": "https://img.olx.com.br/images/74/740483478101099.webp",
            "thumbnail": "https://img.olx.com.br/thumbs/74/740483478101099.jpg"
        },
        {
            "original": "https://img.olx.com.br/images/75/752464952051241.jpg",
            "originalAlt": "Apartamento - / Residencial / Centro - Foto 4",
            "originalWebP": "https://img.olx.com.br/images/75/752464952051241.webp",
            "thumbnail": "https://img.olx.com.br/thumbs/75/752464952051241.jpg"
        },
        {
            "original": "https://img.olx.com.br/images/75/753444836515241.jpg",
            "originalAlt": "Apartamento - / Residencial / Centro - Foto 5",
            "originalWebP": "https://img.olx.com.br/images/75/753444836515241.webp",
            "thumbnail": "https://img.olx.com.br/thumbs/75/753444836515241.jpg"
        },
        {
            "original": "https://img.olx.com.br/images/74/740420838107399.jpg",
            "originalAlt": "Apartamento - / Residencial / Centro - Foto 6",
            "originalWebP": "https://img.olx.com.br/images/74/740420838107399.webp",
            "thumbnail": "https://img.olx.com.br/thumbs/74/740420838107399.jpg"
        },
        {
            "original": "https://img.olx.com.br/images/75/759437114966319.jpg",
            "originalAlt": "Apartamento - / Residencial / Centro - Foto 7",
            "originalWebP": "https://img.olx.com.br/images/75/759437114966319.webp",
            "thumbnail": "https://img.olx.com.br/thumbs/75/759437114966319.jpg"
        },
        {
            "original": "https://img.olx.com.br/images/75/758427716737665.jpg",
            "originalAlt": "Apartamento - / Residencial / Centro - Foto 8",
            "originalWebP": "https://img.olx.com.br/images/75/758427716737665.webp",
            "thumbnail": "https://img.olx.com.br/thumbs/75/758427716737665.jpg"
        },
        {
            "original": "https://img.olx.com.br/images/75/756474837353379.jpg",
            "originalAlt": "Apartamento - / Residencial / Centro - Foto 9",
            "originalWebP": "https://img.olx.com.br/images/75/756474837353379.webp",
            "thumbnail": "https://img.olx.com.br/thumbs/75/756474837353379.jpg"
        },
        {
            "original": "https://img.olx.com.br/images/74/748440958610913.jpg",
            "originalAlt": "Apartamento - / Residencial / Centro - Foto 10",
            "originalWebP": "https://img.olx.com.br/images/74/748440958610913.webp",
            "thumbnail": "https://img.olx.com.br/thumbs/74/748440958610913.jpg"
        },
        {
            "original": "https://img.olx.com.br/images/75/752423716532391.jpg",
            "originalAlt": "Apartamento - / Residencial / Centro - Foto 11",
            "originalWebP": "https://img.olx.com.br/images/75/752423716532391.webp",
            "thumbnail": "https://img.olx.com.br/thumbs/75/752423716532391.jpg"
        },
        {
            "original": "https://img.olx.com.br/images/75/757484352270750.jpg",
            "originalAlt": "Apartamento - / Residencial / Centro - Foto 12",
            "originalWebP": "https://img.olx.com.br/images/75/757484352270750.webp",
            "thumbnail": "https://img.olx.com.br/thumbs/75/757484352270750.jpg"
        },
        {
            "original": "https://img.olx.com.br/images/75/757443358673579.jpg",
            "originalAlt": "Apartamento - / Residencial / Centro - Foto 13",
            "originalWebP": "https://img.olx.com.br/images/75/757443358673579.webp",
            "thumbnail": "https://img.olx.com.br/thumbs/75/757443358673579.jpg"
        },
        {
            "original": "https://img.olx.com.br/images/75/754403470355487.jpg",
            "originalAlt": "Apartamento - / Residencial / Centro - Foto 14",
            "originalWebP": "https://img.olx.com.br/images/75/754403470355487.webp",
            "thumbnail": "https://img.olx.com.br/thumbs/75/754403470355487.jpg"
        },
        {
            "original": "https://img.olx.com.br/images/75/756461715602011.jpg",
            "originalAlt": "Apartamento - / Residencial / Centro - Foto 15",
            "originalWebP": "https://img.olx.com.br/images/75/756461715602011.webp",
            "thumbnail": "https://img.olx.com.br/thumbs/75/756461715602011.jpg"
        },
        {
            "original": "https://img.olx.com.br/images/75/754461598160858.jpg",
            "originalAlt": "Apartamento - / Residencial / Centro - Foto 16",
            "originalWebP": "https://img.olx.com.br/images/75/754461598160858.webp",
            "thumbnail": "https://img.olx.com.br/thumbs/75/754461598160858.jpg"
        },
        {
            "original": "https://img.olx.com.br/images/75/754471234082642.jpg",
            "originalAlt": "Apartamento - / Residencial / Centro - Foto 17",
            "originalWebP": "https://img.olx.com.br/images/75/754471234082642.webp",
            "thumbnail": "https://img.olx.com.br/thumbs/75/754471234082642.jpg"
        },
        {
            "original": "https://img.olx.com.br/images/76/768440472493856.jpg",
            "originalAlt": "Apartamento - / Residencial / Centro - Foto 18",
            "originalWebP": "https://img.olx.com.br/images/76/768440472493856.webp",
            "thumbnail": "https://img.olx.com.br/thumbs/76/768440472493856.jpg"
        },
        {
            "original": "https://img.olx.com.br/images/75/757420476407790.jpg",
            "originalAlt": "Apartamento - / Residencial / Centro - Foto 19",
            "originalWebP": "https://img.olx.com.br/images/75/757420476407790.webp",
            "thumbnail": "https://img.olx.com.br/thumbs/75/757420476407790.jpg"
        },
        {
            "original": "https://img.olx.com.br/images/75/750441352168691.jpg",
            "originalAlt": "Apartamento - / Residencial / Centro - Foto 20",
            "originalWebP": "https://img.olx.com.br/images/75/750441352168691.webp",
            "thumbnail": "https://img.olx.com.br/thumbs/75/750441352168691.jpg"
        }
    ],
    "videoCount": 0,
    "isChatEnabled": false,
    "fixedOnTop": false,
    "url": "https://rj.olx.com.br/rio-de-janeiro-e-regiao/imoveis/apartamento--residencial-centro-1362227309",
    "thumbnail": "https://img.olx.com.br/thumbs256x256/74/741450235160074.jpg",
    "date": 1734052505,
    "imageCount": 20,
    "location": "Rio de Janeiro, Centro",
    "locationDetails": {
        "municipality": "Rio de Janeiro",
        "ddd": "21",
        "neighbourhood": "Centro",
        "uf": "RJ"
    },
    "category": "Apartamentos",
    "searchCategoryLevelZero": 1000,
    "searchCategoryLevelOne": 1001,
    "properties": [
        {
            "name": "category",
            "label": "Categoria",
            "value": "Apartamentos"
        },
        {
            "name": "real_estate_type",
            "label": "Tipo",
            "value": "Venda - apartamento padrão"
        },
        {
            "name": "condominio",
            "label": "Condomínio",
            "value": "R$ 509"
        },
        {
            "name": "iptu",
            "label": "IPTU",
            "value": "R$ 1.328"
        },
        {
            "name": "size",
            "label": "Área útil",
            "value": "86m²"
        },
        {
            "name": "rooms",
            "label": "Quartos",
            "value": "2"
        },
        {
            "name": "bathrooms",
            "label": "Banheiros",
            "value": "1"
        },
        {
            "name": "re_complex_features",
            "label": "Detalhes do condomínio",
            "value": "Elevador"
        },
        {
            "name": "re_types",
            "label": "Tipo",
            "value": "Padrão"
        }
    ],
    "accountActivityStatus": {
        "isOnline": false
    },
    "position": 45,
    "olxPay": {
        "enabled": false,
        "dynamicBadgeProps": [],
        "transactionalBadges": [],
        "installments": [],
        "isCategoryEligible": false
    },
    "olxPayBadgeEnabled": false,
    "olxDelivery": {
        "enabled": false,
        "weight": null
    },
    "olxDeliveryBadgeEnabled": false,
    "installments": false,
    "vehicleReport": {
        "enabled": false,
        "title": null,
        "description": null,
        "reportLink": null,
        "reportTitle": null,
        "tags": null
    },
    "vehicleTags": [],
    "vehicleHasInspectionReport": false,
    "vehiclePills": null,
    "isFavorited": false,
    "hasRealEstateHighlight": false,
    "trackingSpecificData": [
        {
            "key": "region",
            "value": "Rio de Janeiro e região"
        }
    ],
    "carSpecificData": null
}