{
    "subject": "Apartamento - Padrão / Residencial / Glória",
    "title": "Apartamento - Padrão / Residencial / Glória",
    "price": "R$ 640.000",
    "listId": 1362230328,
    "lastBumpAgeSecs": "0",
    "oldPrice": null,
    "professionalAd": true,
    "priceReductionBadge": false,
    "userGoogleReviewsVisible": false,
    "userGoogleRating": null,
    "isFeatured": false,
    "listingCategoryId": "1001",
    "images": [
        {
            "original": "https://img.olx.com.br/images/23/231439594242948.jpg",
            "originalAlt": "Apartamento - Padrão / Residencial / Glória",
            "originalWebP": "https://img.olx.com.br/images/23/231439594242948.webp",
            "thumbnail": "https://img.olx.com.br/thumbs/23/231439594242948.jpg"
        },
        {
            "original": "https://img.olx.com.br/images/23/235456359674944.jpg",
            "originalAlt": "Apartamento - Padrão / Residencial / Glória - Foto 2",
            "originalWebP": "https://img.olx.com.br/images/23/235456359674944.webp",
            "thumbnail": "https://img.olx.com.br/thumbs/23/235456359674944.jpg"
        },
        {
            "original": "https://img.olx.com.br/images/23/239482597408148.jpg",
            "originalAlt": "Apartamento - Padrão / Residencial / Glória - Foto 3",
            "originalWebP": "https://img.olx.com.br/images/23/239482597408148.webp",
            "thumbnail": "https://img.olx.com.br/thumbs/23/239482597408148.jpg"
        },
        {
            "original": "https://img.olx.com.br/images/25/253445958858901.jpg",
            "originalAlt": "Apartamento - Padrão / Residencial / Glória - Foto 4",
            "originalWebP": "https://img.olx.com.br/images/25/253445958858901.webp",
            "thumbnail": "https://img.olx.com.br/thumbs/25/253445958858901.jpg"
        },
        {
            "original": "https://img.olx.com.br/images/23/234493352843708.jpg",
            "originalAlt": "Apartamento - Padrão / Residencial / Glória - Foto 5",
            "originalWebP": "https://img.olx.com.br/images/23/234493352843708.webp",
            "thumbnail": "https://img.olx.com.br/thumbs/23/234493352843708.jpg"
        },
        {
            "original": "https://img.olx.com.br/images/23/230422831269956.jpg",
            "originalAlt": "Apartamento - Padrão / Residencial / Glória - Foto 6",
            "originalWebP": "https://img.olx.com.br/images/23/230422831269956.webp",
            "thumbnail": "https://img.olx.com.br/thumbs/23/230422831269956.jpg"
        },
        {
            "original": "https://img.olx.com.br/images/23/238454355897325.jpg",
            "originalAlt": "Apartamento - Padrão / Residencial / Glória - Foto 7",
            "originalWebP": "https://img.olx.com.br/images/23/238454355897325.webp",
            "thumbnail": "https://img.olx.com.br/thumbs/23/238454355897325.jpg"
        },
        {
            "original": "https://img.olx.com.br/images/25/258487594223447.jpg",
            "originalAlt": "Apartamento - Padrão / Residencial / Glória - Foto 8",
            "originalWebP": "https://img.olx.com.br/images/25/258487594223447.webp",
            "thumbnail": "https://img.olx.com.br/thumbs/25/258487594223447.jpg"
        },
        {
            "original": "https://img.olx.com.br/images/23/234452237401778.jpg",
            "originalAlt": "Apartamento - Padrão / Residencial / Glória - Foto 9",
            "originalWebP": "https://img.olx.com.br/images/23/234452237401778.webp",
            "thumbnail": "https://img.olx.com.br/thumbs/23/234452237401778.jpg"
        },
        {
            "original": "https://img.olx.com.br/images/23/230438837182554.jpg",
            "originalAlt": "Apartamento - Padrão / Residencial / Glória - Foto 10",
            "originalWebP": "https://img.olx.com.br/images/23/230438837182554.webp",
            "thumbnail": "https://img.olx.com.br/thumbs/23/230438837182554.jpg"
        },
        {
            "original": "https://img.olx.com.br/images/23/236478239608430.jpg",
            "originalAlt": "Apartamento - Padrão / Residencial / Glória - Foto 11",
            "originalWebP": "https://img.olx.com.br/images/23/236478239608430.webp",
            "thumbnail": "https://img.olx.com.br/thumbs/23/236478239608430.jpg"
        },
        {
            "original": "https://img.olx.com.br/images/23/238474951196978.jpg",
            "originalAlt": "Apartamento - Padrão / Residencial / Glória - Foto 12",
            "originalWebP": "https://img.olx.com.br/images/23/238474951196978.webp",
            "thumbnail": "https://img.olx.com.br/thumbs/23/238474951196978.jpg"
        },
        {
            "original": "https://img.olx.com.br/images/23/235453476633467.jpg",
            "originalAlt": "Apartamento - Padrão / Residencial / Glória - Foto 13",
            "originalWebP": "https://img.olx.com.br/images/23/235453476633467.webp",
            "thumbnail": "https://img.olx.com.br/thumbs/23/235453476633467.jpg"
        },
        {
            "original": "https://img.olx.com.br/images/23/239405238587606.jpg",
            "originalAlt": "Apartamento - Padrão / Residencial / Glória - Foto 14",
            "originalWebP": "https://img.olx.com.br/images/23/239405238587606.webp",
            "thumbnail": "https://img.olx.com.br/thumbs/23/239405238587606.jpg"
        },
        {
            "original": "https://img.olx.com.br/images/23/235461352739744.jpg",
            "originalAlt": "Apartamento - Padrão / Residencial / Glória - Foto 15",
            "originalWebP": "https://img.olx.com.br/images/23/235461352739744.webp",
            "thumbnail": "https://img.olx.com.br/thumbs/23/235461352739744.jpg"
        },
        {
            "original": "https://img.olx.com.br/images/23/234441714480619.jpg",
            "originalAlt": "Apartamento - Padrão / Residencial / Glória - Foto 16",
            "originalWebP": "https://img.olx.com.br/images/23/234441714480619.webp",
            "thumbnail": "https://img.olx.com.br/thumbs/23/234441714480619.jpg"
        },
        {
            "original": "https://img.olx.com.br/images/23/234488591830472.jpg",
            "originalAlt": "Apartamento - Padrão / Residencial / Glória - Foto 17",
            "originalWebP": "https://img.olx.com.br/images/23/234488591830472.webp",
            "thumbnail": "https://img.olx.com.br/thumbs/23/234488591830472.jpg"
        },
        {
            "original": "https://img.olx.com.br/images/23/233420117560633.jpg",
            "originalAlt": "Apartamento - Padrão / Residencial / Glória - Foto 18",
            "originalWebP": "https://img.olx.com.br/images/23/233420117560633.webp",
            "thumbnail": "https://img.olx.com.br/thumbs/23/233420117560633.jpg"
        },
        {
            "original": "https://img.olx.com.br/images/23/236462351077117.jpg",
            "originalAlt": "Apartamento - Padrão / Residencial / Glória - Foto 19",
            "originalWebP": "https://img.olx.com.br/images/23/236462351077117.webp",
            "thumbnail": "https://img.olx.com.br/thumbs/23/236462351077117.jpg"
        },
        {
            "original": "https://img.olx.com.br/images/24/247445479063380.jpg",
            "originalAlt": "Apartamento - Padrão / Residencial / Glória - Foto 20",
            "originalWebP": "https://img.olx.com.br/images/24/247445479063380.webp",
            "thumbnail": "https://img.olx.com.br/thumbs/24/247445479063380.jpg"
        }
    ],
    "videoCount": 0,
    "isChatEnabled": false,
    "fixedOnTop": false,
    "url": "https://rj.olx.com.br/rio-de-janeiro-e-regiao/imoveis/apartamento-padrao-residencial-gloria-1362230328",
    "thumbnail": "https://img.olx.com.br/thumbs256x256/23/231439594242948.jpg",
    "date": 1734053050,
    "imageCount": 20,
    "location": "Rio de Janeiro, Glória",
    "locationDetails": {
        "municipality": "Rio de Janeiro",
        "ddd": "21",
        "neighbourhood": "Glória",
        "uf": "RJ"
    },
    "category": "Apartamentos",
    "searchCategoryLevelZero": 1000,
    "searchCategoryLevelOne": 1001,
    "properties": [
        {
            "name": "category",
            "label": "Categoria",
            "value": "Apartamentos"
        },
        {
            "name": "real_estate_type",
            "label": "Tipo",
            "value": "Venda - apartamento padrão"
        },
        {
            "name": "condominio",
            "label": "Condomínio",
            "value": "R$ 720"
        },
        {
            "name": "iptu",
            "label": "IPTU",
            "value": "R$ 1.800"
        },
        {
            "name": "size",
            "label": "Área útil",
            "value": "85m²"
        },
        {
            "name": "rooms",
            "label": "Quartos",
            "value": "3"
        },
        {
            "name": "bathrooms",
            "label": "Banheiros",
            "value": "2"
        },
        {
            "name": "re_complex_features",
            "label": "Detalhes do condomínio",
            "value": "Elevador"
        },
        {
            "name": "re_types",
            "label": "Tipo",
            "value": "Padrão"
        }
    ],
    "accountActivityStatus": {
        "isOnline": false
    },
    "position": 17,
    "olxPay": {
        "enabled": false,
        "dynamicBadgeProps": [],
        "transactionalBadges": [],
        "installments": [],
        "isCategoryEligible": false
    },
    "olxPayBadgeEnabled": false,
    "olxDelivery": {
        "enabled": false,
        "weight": null
    },
    "olxDeliveryBadgeEnabled": false,
    "installments": false,
    "vehicleReport": {
        "enabled": false,
        "title": null,
        "description": null,
        "reportLink": null,
        "reportTitle": null,
        "tags": null
    },
    "vehicleTags": [],
    "vehicleHasInspectionReport": false,
    "vehiclePills": null,
    "isFavorited": false,
    "hasRealEstateHighlight": false,
    "trackingSpecificData": [
        {
            "key": "region",
            "value": "Rio de Janeiro e região"
        }
    ],
    "carSpecificData": null
}